{
  "$schema": "https://raw.githubusercontent.com/JanDeDobbeleer/oh-my-posh/main/themes/schema.json",
  "blocks": [
    {
      "alignment": "left",
      "segments": [
        {
          "background": "#4F90DB",
          "foreground": "#FAFAFA",
          "style": "powerline",
          "template": " {{ .Icon }} ",
          "type": "os"
        },
        {
          "background": "#DB9165",
          "foreground": "#060606",
          "powerline_symbol": "\ue0b0",
          "properties": {
            "enabled": "true"
          },
          "style": "powerline",
          "template": " \uf0e7 ",
          "type": "root"
        },
        {
          "background": "#213C5C",
          "foreground": "#FAFAFA",
          "powerline_symbol": "\ue0b0",
          "style": "powerline",
          "template": " {{ .UserName }}@{{ .HostName }} ",
          "type": "text"
        },
        {
          "background": "#4F90DB",
          "foreground": "#FAFAFA",
          "powerline_symbol": "\ue0b0",
          "properties": {
            "style": "folder"
          },
          "style": "powerline",
          "template": " \ue5ff {{ .Path }} ",
          "type": "path"
        },
        {
          "background": "#596675",
          "foreground": "#FAFAFA",
          "powerline_symbol": "\ue0b0",
          "properties": {
            "fetch_stash_count": true,
            "fetch_status": true,
            "fetch_upstream_icon": true
          },
          "style": "powerline",
          "template": " {{ .UpstreamIcon }}{{ .HEAD }}{{ .BranchStatus }}{{ if .Working.Changed }} \uf044 {{ .Working.String }}{{ end }}{{ if and (.Working.Changed) (.Staging.Changed) }} |{{ end }}{{ if .Staging.Changed }} \uf046 {{ .Staging.String }}{{ end }}{{ if gt .StashCount 0 }} \uf692 {{ .StashCount }}{{ end }} ",
          "type": "git"
        },
        {
          "background": "#DBC239",
          "foreground": "#060606",
          "powerline_symbol": "\ue0b0",
          "style": "powerline",
          "template": " \ufbab{{ .FormattedMs }} ",
          "type": "executiontime"
        },
        {
          "background": "#DB65BA",
          "foreground": "#060606",
          "powerline_symbol": "\ue0b0",
          "style": "powerline",
          "template": " \ue23a {{ .Code }} ",
          "type": "exit"
        }
      ],
      "type": "prompt"
    },
    {
      "alignment": "right",
      "segments": [
        {
          "background": "#232F38",
          "foreground": "#FFA400",
          "powerline_symbol": "\ue0b0",
          "style": "powerline",
          "template": "\ue7ad {{.Profile}}{{if .Region}}@{{.Region}}{{end}}",
          "type": "aws"
        },
        {
          "background": "#0078D4",
          "foreground": "#FFFFFF",
          "powerline_symbol": "\ue0b0",
          "style": "powerline",
          "template": "\ufd03 {{ .EnvironmentName }}",
          "type": "az"
        },
        {
          "foreground": "#6997C9",
          "properties": {
            "time_format": "15:04:05"
          },
          "style": "plain",
          "template": " {{ .CurrentDate | date .Format }} ",
          "type": "time"
        }
      ],
      "type": "prompt"
    },
    {
      "alignment": "left",
      "newline": true,
      "segments": [
        {
          "foreground": "#FAFAFA",
          "properties": {
            "mapped_shell_names": {
              "pwsh": "ps"
            }
          },
          "style": "powerline",
          "template": "{{ .Name }}\u276f",
          "type": "shell"
        }
      ],
      "type": "prompt"
    }
  ],
  "console_title_template": "{{.Folder}}{{if .Root}} :: root{{end}} :: {{.Shell}}",
  "final_space": true,
  "version": 2
}
